{
  "parameter": "offset_voltage",
  "unit": "mV",
  "pat_lower": -6.0403,
  "pat_upper": 6.0579,
  "spec_lower": -8.0,
  "spec_upper": 8.0,
  "shift_mv": 4.31,
  "reference": {
    "mean": 0.0166,
    "cpk": 2.6395,
    "bins": [
      {
        "x0": -8.5,
        "x1": -8.046104269241637,
        "count": 0
      },
      {
        "x0": -8.046104269241637,
        "x1": -7.592208538483274,
        "count": 7
      },
      {
        "x0": -7.592208538483274,
        "x1": -7.138312807724912,
        "count": 11
      },
      {
        "x0": -7.138312807724912,
        "x1": -6.6844170769665485,
        "count": 10
      },
      {
        "x0": -6.6844170769665485,
        "x1": -6.230521346208186,
        "count": 8
      },
      {
        "x0": -6.230521346208186,
        "x1": -5.776625615449824,
        "count": 0
      },
      {
        "x0": -5.776625615449824,
        "x1": -5.32272988469146,
        "count": 0
      },
      {
        "x0": -5.32272988469146,
        "x1": -4.868834153933098,
        "count": 0
      },
      {
        "x0": -4.868834153933098,
        "x1": -4.4149384231747355,
        "count": 0
      },
      {
        "x0": -4.4149384231747355,
        "x1": -3.961042692416372,
        "count": 0
      },
      {
        "x0": -3.961042692416372,
        "x1": -3.5071469616580098,
        "count": 2
      },
      {
        "x0": -3.5071469616580098,
        "x1": -3.0532512308996473,
        "count": 8
      },
      {
        "x0": -3.0532512308996473,
        "x1": -2.599355500141284,
        "count": 24
      },
      {
        "x0": -2.599355500141284,
        "x1": -2.1454597693829216,
        "count": 65
      },
      {
        "x0": -2.1454597693829216,
        "x1": -1.6915640386245583,
        "count": 181
      },
      {
        "x0": -1.6915640386245583,
        "x1": -1.2376683078661959,
        "count": 363
      },
      {
        "x0": -1.2376683078661959,
        "x1": -0.7837725771078334,
        "count": 629
      },
      {
        "x0": -0.7837725771078334,
        "x1": -0.329876846349471,
        "count": 869
      },
      {
        "x0": -0.329876846349471,
        "x1": 0.1240188844088923,
        "count": 1080
      },
      {
        "x0": 0.1240188844088923,
        "x1": 0.5779146151672556,
        "count": 1018
      },
      {
        "x0": 0.5779146151672556,
        "x1": 1.0318103459256172,
        "count": 741
      },
      {
        "x0": 1.0318103459256172,
        "x1": 1.4857060766839805,
        "count": 498
      },
      {
        "x0": 1.4857060766839805,
        "x1": 1.9396018074423438,
        "count": 261
      },
      {
        "x0": 1.9396018074423438,
        "x1": 2.3934975382007053,
        "count": 129
      },
      {
        "x0": 2.3934975382007053,
        "x1": 2.8473932689590686,
        "count": 43
      },
      {
        "x0": 2.8473932689590686,
        "x1": 3.301288999717432,
        "count": 17
      },
      {
        "x0": 3.301288999717432,
        "x1": 3.7551847304757953,
        "count": 2
      },
      {
        "x0": 3.7551847304757953,
        "x1": 4.209080461234157,
        "count": 0
      },
      {
        "x0": 4.209080461234157,
        "x1": 4.66297619199252,
        "count": 0
      },
      {
        "x0": 4.66297619199252,
        "x1": 5.116871922750883,
        "count": 0
      },
      {
        "x0": 5.116871922750883,
        "x1": 5.570767653509245,
        "count": 0
      },
      {
        "x0": 5.570767653509245,
        "x1": 6.024663384267608,
        "count": 0
      },
      {
        "x0": 6.024663384267608,
        "x1": 6.478559115025972,
        "count": 4
      },
      {
        "x0": 6.478559115025972,
        "x1": 6.932454845784333,
        "count": 11
      },
      {
        "x0": 6.932454845784333,
        "x1": 7.3863505765426964,
        "count": 3
      },
      {
        "x0": 7.3863505765426964,
        "x1": 7.840246307301058,
        "count": 3
      },
      {
        "x0": 7.840246307301058,
        "x1": 8.294142038059423,
        "count": 3
      },
      {
        "x0": 8.294142038059423,
        "x1": 8.748037768817785,
        "count": 4
      },
      {
        "x0": 8.748037768817785,
        "x1": 9.201933499576146,
        "count": 6
      },
      {
        "x0": 9.201933499576146,
        "x1": 9.65582923033451,
        "count": 0
      }
    ]
  },
  "lot10": {
    "mean": 4.3234,
    "cpk": 1.1484,
    "yield_loss": 0.06422,
    "fp_count": 63,
    "bins": [
      {
        "x0": -8.5,
        "x1": -8.046104269241637,
        "count": 0
      },
      {
        "x0": -8.046104269241637,
        "x1": -7.592208538483274,
        "count": 3
      },
      {
        "x0": -7.592208538483274,
        "x1": -7.138312807724912,
        "count": 1
      },
      {
        "x0": -7.138312807724912,
        "x1": -6.6844170769665485,
        "count": 1
      },
      {
        "x0": -6.6844170769665485,
        "x1": -6.230521346208186,
        "count": 0
      },
      {
        "x0": -6.230521346208186,
        "x1": -5.776625615449824,
        "count": 0
      },
      {
        "x0": -5.776625615449824,
        "x1": -5.32272988469146,
        "count": 0
      },
      {
        "x0": -5.32272988469146,
        "x1": -4.868834153933098,
        "count": 0
      },
      {
        "x0": -4.868834153933098,
        "x1": -4.4149384231747355,
        "count": 0
      },
      {
        "x0": -4.4149384231747355,
        "x1": -3.961042692416372,
        "count": 0
      },
      {
        "x0": -3.961042692416372,
        "x1": -3.5071469616580098,
        "count": 0
      },
      {
        "x0": -3.5071469616580098,
        "x1": -3.0532512308996473,
        "count": 0
      },
      {
        "x0": -3.0532512308996473,
        "x1": -2.599355500141284,
        "count": 0
      },
      {
        "x0": -2.599355500141284,
        "x1": -2.1454597693829216,
        "count": 0
      },
      {
        "x0": -2.1454597693829216,
        "x1": -1.6915640386245583,
        "count": 0
      },
      {
        "x0": -1.6915640386245583,
        "x1": -1.2376683078661959,
        "count": 0
      },
      {
        "x0": -1.2376683078661959,
        "x1": -0.7837725771078334,
        "count": 0
      },
      {
        "x0": -0.7837725771078334,
        "x1": -0.329876846349471,
        "count": 0
      },
      {
        "x0": -0.329876846349471,
        "x1": 0.1240188844088923,
        "count": 0
      },
      {
        "x0": 0.1240188844088923,
        "x1": 0.5779146151672556,
        "count": 0
      },
      {
        "x0": 0.5779146151672556,
        "x1": 1.0318103459256172,
        "count": 0
      },
      {
        "x0": 1.0318103459256172,
        "x1": 1.4857060766839805,
        "count": 2
      },
      {
        "x0": 1.4857060766839805,
        "x1": 1.9396018074423438,
        "count": 8
      },
      {
        "x0": 1.9396018074423438,
        "x1": 2.3934975382007053,
        "count": 21
      },
      {
        "x0": 2.3934975382007053,
        "x1": 2.8473932689590686,
        "count": 43
      },
      {
        "x0": 2.8473932689590686,
        "x1": 3.301288999717432,
        "count": 73
      },
      {
        "x0": 3.301288999717432,
        "x1": 3.7551847304757953,
        "count": 142
      },
      {
        "x0": 3.7551847304757953,
        "x1": 4.209080461234157,
        "count": 159
      },
      {
        "x0": 4.209080461234157,
        "x1": 4.66297619199252,
        "count": 180
      },
      {
        "x0": 4.66297619199252,
        "x1": 5.116871922750883,
        "count": 135
      },
      {
        "x0": 5.116871922750883,
        "x1": 5.570767653509245,
        "count": 89
      },
      {
        "x0": 5.570767653509245,
        "x1": 6.024663384267608,
        "count": 74
      },
      {
        "x0": 6.024663384267608,
        "x1": 6.478559115025972,
        "count": 36
      },
      {
        "x0": 6.478559115025972,
        "x1": 6.932454845784333,
        "count": 11
      },
      {
        "x0": 6.932454845784333,
        "x1": 7.3863505765426964,
        "count": 15
      },
      {
        "x0": 7.3863505765426964,
        "x1": 7.840246307301058,
        "count": 2
      },
      {
        "x0": 7.840246307301058,
        "x1": 8.294142038059423,
        "count": 0
      },
      {
        "x0": 8.294142038059423,
        "x1": 8.748037768817785,
        "count": 3
      },
      {
        "x0": 8.748037768817785,
        "x1": 9.201933499576146,
        "count": 2
      },
      {
        "x0": 9.201933499576146,
        "x1": 9.65582923033451,
        "count": 0
      }
    ]
  },
  "lot_cpk_trend": [
    {
      "lot_id": "LOT01",
      "cpk": 1.8213,
      "role": "reference",
      "drifted": false
    },
    {
      "lot_id": "LOT02",
      "cpk": 2.0052,
      "role": "reference",
      "drifted": false
    },
    {
      "lot_id": "LOT03",
      "cpk": 2.1374,
      "role": "reference",
      "drifted": false
    },
    {
      "lot_id": "LOT04",
      "cpk": 2.2509,
      "role": "reference",
      "drifted": false
    },
    {
      "lot_id": "LOT05",
      "cpk": 2.0854,
      "role": "reference",
      "drifted": false
    },
    {
      "lot_id": "LOT06",
      "cpk": 2.1474,
      "role": "reference",
      "drifted": false
    },
    {
      "lot_id": "LOT07",
      "cpk": 2.3295,
      "role": "holdout",
      "drifted": false
    },
    {
      "lot_id": "LOT08",
      "cpk": 1.8461,
      "role": "holdout",
      "drifted": false
    },
    {
      "lot_id": "LOT09",
      "cpk": 1.6387,
      "role": "holdout",
      "drifted": false
    },
    {
      "lot_id": "LOT10",
      "cpk": 1.1484,
      "role": "holdout",
      "drifted": true
    }
  ]
}